cp2k_to_deepmdkit/__init__.py
cp2k_to_deepmdkit/box.py
cp2k_to_deepmdkit/convert.py
cp2k_to_deepmdkit/coord.py
cp2k_to_deepmdkit/force_energy.py
cp2k_2_deepmdkit-1.0.1.dist-info/LICENSE
cp2k_2_deepmdkit-1.0.1.dist-info/METADATA
cp2k_2_deepmdkit-1.0.1.dist-info/WHEEL
cp2k_2_deepmdkit-1.0.1.dist-info/entry_points.txt
cp2k_2_deepmdkit-1.0.1.dist-info/top_level.txt
cp2k_2_deepmdkit-1.0.1.dist-info/RECORD
