Metadata-Version: 2.1
Name: cp2k_2_deepmdkit
Version: 1.0.1
License-File: LICENSE
